[{"class": "NORM.MISML", "bbox": [280, 133, 312, 165]}, {"class": "NORM.YPSILONSML", "bbox": [310, 413, 342, 445]}, {"class": "SUFF.BETACAP", "bbox": [128, 409, 160, 441]}, {"class": "NORM.ALPHASML", "bbox": [320, 380, 352, 412]}, {"class": "SUFF.MICAP", "bbox": [363, 407, 395, 439]}, {"class": "SUFF.TAUCAP", "bbox": [88, 63, 120, 95]}, {"class": "SUFF.DELTACAP", "bbox": [382, 290, 414, 322]}, {"class": "NORM.ZETASML", "bbox": [169, 276, 201, 308]}, {"class": "SUFF.PIISML", "bbox": [367, 125, 399, 157]}, {"class": "NORM.ROSML", "bbox": [31, 261, 63, 293]}, {"class": "SUFF.OMEGASML", "bbox": [202, 237, 234, 269]}, {"class": "NORM.YPSILONSML", "bbox": [299, 21, 331, 53]}, {"class": "SUFF.LAMDASML", "bbox": [366, 42, 398, 74]}, {"class": "SUFF.XICAP", "bbox": [256, 310, 288, 342]}, {"class": "SUFF.THETASML", "bbox": [132, 211, 164, 243]}, {"class": "SUFF.IOTASML", "bbox": [20, 310, 52, 342]}, {"class": "NORM.YPSILONSML", "bbox": [255, 64, 287, 96]}, {"class": "NORM.ZETACAP", "bbox": [76, 176, 108, 208]}, {"class": "SUFF.ZETACAP", "bbox": [413, 189, 445, 221]}, {"class": "SUFF.THETASML", "bbox": [83, 256, 115, 288]}]