[{"class": "SUFF.FICAP", "bbox": [209, 109, 241, 141]}, {"class": "NORM.TAUCAP", "bbox": [80, 49, 112, 81]}, {"class": "SUFF.KAPASML", "bbox": [163, 59, 195, 91]}, {"class": "NORM.IOTASML", "bbox": [299, 344, 331, 376]}, {"class": "SUFF.OMEGACAP", "bbox": [402, 297, 434, 329]}, {"class": "NORM.XICAP", "bbox": [179, 336, 211, 368]}, {"class": "NORM.ALPHACAP", "bbox": [11, 17, 43, 49]}, {"class": "NORM.KAPACAP", "bbox": [72, 125, 104, 157]}, {"class": "SUFF.DELTASML", "bbox": [150, 236, 182, 268]}, {"class": "SUFF.MICAP", "bbox": [320, 154, 352, 186]}, {"class": "NORM.YPSILONCAP", "bbox": [322, 231, 354, 263]}, {"class": "NORM.EPSILONSML", "bbox": [236, 195, 268, 227]}, {"class": "SUFF.EPSILONCAP", "bbox": [372, 97, 404, 129]}, {"class": "NORM.ALPHASML", "bbox": [50, 15, 82, 47]}, {"class": "SUFF.ZETACAP", "bbox": [298, 308, 330, 340]}, {"class": "NORM.LAMDASML", "bbox": [193, 397, 225, 429]}, {"class": "SUFF.THETACAP", "bbox": [97, 305, 129, 337]}, {"class": "NORM.SIGMACAP", "bbox": [118, 338, 150, 370]}, {"class": "NORM.HETACAP", "bbox": [374, 62, 406, 94]}, {"class": "NORM.LAMDASML", "bbox": [402, 142, 434, 174]}]