[{"class": "NORM.NISML", "bbox": [324, 99, 356, 131]}, {"class": "SUFF.OMEGASML", "bbox": [275, 33, 307, 65]}, {"class": "SUFF.NICAP", "bbox": [305, 354, 337, 386]}, {"class": "NORM.MISML", "bbox": [170, 307, 202, 339]}, {"class": "SUFF.XICAP", "bbox": [154, 40, 186, 72]}, {"class": "SUFF.MISML", "bbox": [272, 379, 304, 411]}, {"class": "SUFF.EPSILONCAP", "bbox": [255, 219, 287, 251]}, {"class": "NORM.SIGMACAP", "bbox": [254, 282, 286, 314]}, {"class": "SUFF.NISML", "bbox": [63, 74, 95, 106]}, {"class": "SUFF.YPSILONCAP", "bbox": [253, 416, 285, 448]}, {"class": "SUFF.EPSILONCAP", "bbox": [379, 36, 411, 68]}, {"class": "NORM.PIICAP", "bbox": [158, 112, 190, 144]}, {"class": "NORM.KSICAP", "bbox": [302, 163, 334, 195]}, {"class": "SUFF.XISML", "bbox": [2, 226, 34, 258]}, {"class": "SUFF.KSICAP", "bbox": [155, 80, 187, 112]}, {"class": "SUFF.OMEGASML", "bbox": [68, 164, 100, 196]}, {"class": "SUFF.OMIKRONSML", "bbox": [144, 360, 176, 392]}, {"class": "NORM.OMEGACAP", "bbox": [46, 265, 78, 297]}, {"class": "SUFF.KAPASML", "bbox": [358, 148, 390, 180]}, {"class": "SUFF.NICAP", "bbox": [381, 295, 413, 327]}]