[{"class": "SUFF.DELTACAP", "bbox": [310, 240, 342, 272]}, {"class": "SUFF.THETACAP", "bbox": [244, 139, 276, 171]}, {"class": "SUFF.PSISML", "bbox": [85, 302, 117, 334]}, {"class": "NORM.XISML", "bbox": [152, 342, 184, 374]}, {"class": "NORM.OMIKRONSML", "bbox": [358, 174, 390, 206]}, {"class": "NORM.SIGMACAP", "bbox": [129, 103, 161, 135]}, {"class": "SUFF.OMEGACAP", "bbox": [32, 241, 64, 273]}, {"class": "SUFF.KAPASML", "bbox": [189, 313, 221, 345]}, {"class": "NORM.GAMMACAP", "bbox": [295, 71, 327, 103]}, {"class": "SUFF.DELTACAP", "bbox": [363, 229, 395, 261]}, {"class": "SUFF.TAUCAP", "bbox": [259, 239, 291, 271]}, {"class": "NORM.PIISML", "bbox": [301, 348, 333, 380]}, {"class": "SUFF.SIGMASML", "bbox": [34, 409, 66, 441]}, {"class": "NORM.LAMDACAP", "bbox": [296, 387, 328, 419]}, {"class": "SUFF.NISML", "bbox": [201, 252, 233, 284]}, {"class": "SUFF.THETACAP", "bbox": [24, 125, 56, 157]}, {"class": "SUFF.MISML", "bbox": [20, 63, 52, 95]}, {"class": "SUFF.MISML", "bbox": [45, 273, 77, 305]}, {"class": "NORM.SIGMASML", "bbox": [107, 138, 139, 170]}, {"class": "SUFF.LAMDACAP", "bbox": [258, 348, 290, 380]}]