[{"class": "NORM.PIISML", "bbox": [328, 36, 360, 68]}, {"class": "NORM.OMEGASML", "bbox": [146, 72, 178, 104]}, {"class": "NORM.OMIKRONSML", "bbox": [292, 21, 324, 53]}, {"class": "NORM.OMEGASML", "bbox": [24, 65, 56, 97]}, {"class": "SUFF.PSICAP", "bbox": [300, 125, 332, 157]}, {"class": "SUFF.GAMMACAP", "bbox": [214, 314, 246, 346]}, {"class": "NORM.HETASML", "bbox": [284, 172, 316, 204]}, {"class": "SUFF.EPSILONSML", "bbox": [346, 174, 378, 206]}, {"class": "SUFF.SIGMACAP", "bbox": [373, 253, 405, 285]}, {"class": "SUFF.HETACAP", "bbox": [43, 345, 75, 377]}, {"class": "NORM.YPSILONSML", "bbox": [82, 405, 114, 437]}, {"class": "NORM.BETASML", "bbox": [188, 82, 220, 114]}, {"class": "SUFF.GAMMASML", "bbox": [42, 247, 74, 279]}, {"class": "NORM.LAMDACAP", "bbox": [266, 301, 298, 333]}, {"class": "SUFF.HETASML", "bbox": [102, 54, 134, 86]}, {"class": "SUFF.KAPACAP", "bbox": [223, 352, 255, 384]}, {"class": "NORM.ZETACAP", "bbox": [408, 131, 440, 163]}, {"class": "SUFF.OMIKRONCAP", "bbox": [8, 13, 40, 45]}, {"class": "NORM.EPSILONCAP", "bbox": [132, 413, 164, 445]}, {"class": "SUFF.THETACAP", "bbox": [223, 215, 255, 247]}]