[{"class": "NORM.DELTACAP", "bbox": [170, 412, 202, 444]}, {"class": "NORM.LAMDASML", "bbox": [129, 234, 161, 266]}, {"class": "SUFF.TAUCAP", "bbox": [73, 181, 105, 213]}, {"class": "NORM.YPSILONSML", "bbox": [328, 91, 360, 123]}, {"class": "SUFF.BETACAP", "bbox": [59, 317, 91, 349]}, {"class": "SUFF.OMIKRONSML", "bbox": [26, 183, 58, 215]}, {"class": "NORM.FICAP", "bbox": [206, 373, 238, 405]}, {"class": "SUFF.EPSILONCAP", "bbox": [342, 191, 374, 223]}, {"class": "NORM.ROCAP", "bbox": [358, 334, 390, 366]}, {"class": "SUFF.PIICAP", "bbox": [145, 331, 177, 363]}, {"class": "SUFF.ROSML", "bbox": [104, 13, 136, 45]}, {"class": "NORM.KSISML", "bbox": [190, 44, 222, 76]}, {"class": "SUFF.KSISML", "bbox": [159, 272, 191, 304]}, {"class": "NORM.KSISML", "bbox": [19, 315, 51, 347]}, {"class": "SUFF.YPSILONSML", "bbox": [363, 93, 395, 125]}, {"class": "NORM.GAMMASML", "bbox": [84, 74, 116, 106]}, {"class": "SUFF.SIGMASML", "bbox": [208, 277, 240, 309]}, {"class": "NORM.ZETACAP", "bbox": [246, 294, 278, 326]}, {"class": "SUFF.GAMMACAP", "bbox": [265, 6, 297, 38]}, {"class": "NORM.ZETASML", "bbox": [99, 366, 131, 398]}]