[{"class": "SUFF.MISML", "bbox": [71, 392, 103, 424]}, {"class": "NORM.ROCAP", "bbox": [290, 395, 322, 427]}, {"class": "SUFF.GAMMACAP", "bbox": [211, 216, 243, 248]}, {"class": "NORM.FICAP", "bbox": [403, 44, 435, 76]}, {"class": "NORM.KAPASML", "bbox": [189, 98, 221, 130]}, {"class": "SUFF.KAPACAP", "bbox": [158, 187, 190, 219]}, {"class": "SUFF.YPSILONCAP", "bbox": [224, 150, 256, 182]}, {"class": "NORM.MISML", "bbox": [11, 286, 43, 318]}, {"class": "SUFF.ROCAP", "bbox": [373, 221, 405, 253]}, {"class": "SUFF.ALPHASML", "bbox": [394, 362, 426, 394]}, {"class": "NORM.KSICAP", "bbox": [389, 266, 421, 298]}, {"class": "NORM.KAPACAP", "bbox": [366, 175, 398, 207]}, {"class": "NORM.OMEGACAP", "bbox": [192, 333, 224, 365]}, {"class": "NORM.EPSILONCAP", "bbox": [181, 258, 213, 290]}, {"class": "SUFF.LAMDASML", "bbox": [246, 82, 278, 114]}, {"class": "SUFF.KAPACAP", "bbox": [9, 391, 41, 423]}, {"class": "SUFF.GAMMASML", "bbox": [180, 16, 212, 48]}, {"class": "NORM.FISML", "bbox": [15, 170, 47, 202]}, {"class": "NORM.OMEGACAP", "bbox": [360, 123, 392, 155]}, {"class": "NORM.PSICAP", "bbox": [362, 355, 394, 387]}]