[{"class": "SUFF.XISML", "bbox": [228, 299, 260, 331]}, {"class": "NORM.GAMMACAP", "bbox": [140, 21, 172, 53]}, {"class": "NORM.KSISML", "bbox": [117, 266, 149, 298]}, {"class": "SUFF.DELTASML", "bbox": [343, 87, 375, 119]}, {"class": "SUFF.KAPASML", "bbox": [222, 180, 254, 212]}, {"class": "NORM.LAMDASML", "bbox": [168, 207, 200, 239]}, {"class": "NORM.LAMDASML", "bbox": [2, 357, 34, 389]}, {"class": "SUFF.PIISML", "bbox": [216, 370, 248, 402]}, {"class": "SUFF.GAMMASML", "bbox": [4, 226, 36, 258]}, {"class": "SUFF.FICAP", "bbox": [279, 77, 311, 109]}, {"class": "SUFF.XISML", "bbox": [178, 297, 210, 329]}, {"class": "NORM.SIGMASML", "bbox": [369, 254, 401, 286]}, {"class": "NORM.ALPHASML", "bbox": [272, 173, 304, 205]}, {"class": "NORM.HETACAP", "bbox": [191, 61, 223, 93]}, {"class": "SUFF.SIGMACAP", "bbox": [127, 172, 159, 204]}, {"class": "SUFF.IOTACAP", "bbox": [267, 131, 299, 163]}, {"class": "NORM.KSICAP", "bbox": [179, 122, 211, 154]}, {"class": "SUFF.HETASML", "bbox": [77, 386, 109, 418]}, {"class": "SUFF.MICAP", "bbox": [339, 401, 371, 433]}, {"class": "SUFF.NICAP", "bbox": [406, 201, 438, 233]}]