[{"class": "SUFF.SIGMASML", "bbox": [119, 187, 151, 219]}, {"class": "NORM.LAMDACAP", "bbox": [230, 38, 262, 70]}, {"class": "NORM.ALPHACAP", "bbox": [403, 217, 435, 249]}, {"class": "NORM.ROCAP", "bbox": [406, 414, 438, 446]}, {"class": "NORM.OMEGACAP", "bbox": [198, 234, 230, 266]}, {"class": "SUFF.IOTASML", "bbox": [341, 324, 373, 356]}, {"class": "NORM.SIGMACAP", "bbox": [252, 305, 284, 337]}, {"class": "NORM.ZETASML", "bbox": [173, 50, 205, 82]}, {"class": "NORM.IOTASML", "bbox": [319, 127, 351, 159]}, {"class": "NORM.OMIKRONCAP", "bbox": [80, 383, 112, 415]}, {"class": "NORM.OMEGACAP", "bbox": [201, 391, 233, 423]}, {"class": "SUFF.DELTASML", "bbox": [364, 62, 396, 94]}, {"class": "SUFF.KSICAP", "bbox": [304, 71, 336, 103]}, {"class": "NORM.KAPACAP", "bbox": [397, 104, 429, 136]}, {"class": "NORM.HETASML", "bbox": [291, 212, 323, 244]}, {"class": "NORM.MISML", "bbox": [32, 307, 64, 339]}, {"class": "SUFF.XISML", "bbox": [315, 4, 347, 36]}, {"class": "NORM.IOTASML", "bbox": [3, 141, 35, 173]}, {"class": "SUFF.NISML", "bbox": [168, 320, 200, 352]}, {"class": "SUFF.LAMDASML", "bbox": [206, 149, 238, 181]}]