[{"class": "SUFF.HETASML", "bbox": [359, 282, 391, 314]}, {"class": "NORM.OMIKRONCAP", "bbox": [152, 251, 184, 283]}, {"class": "NORM.KAPACAP", "bbox": [188, 391, 220, 423]}, {"class": "SUFF.ROSML", "bbox": [125, 396, 157, 428]}, {"class": "SUFF.FICAP", "bbox": [368, 118, 400, 150]}, {"class": "SUFF.YPSILONCAP", "bbox": [228, 187, 260, 219]}, {"class": "NORM.GAMMACAP", "bbox": [48, 369, 80, 401]}, {"class": "SUFF.PSICAP", "bbox": [361, 383, 393, 415]}, {"class": "SUFF.ROCAP", "bbox": [240, 273, 272, 305]}, {"class": "SUFF.KAPACAP", "bbox": [113, 163, 145, 195]}, {"class": "SUFF.LAMDACAP", "bbox": [410, 298, 442, 330]}, {"class": "NORM.KSICAP", "bbox": [104, 45, 136, 77]}, {"class": "SUFF.XICAP", "bbox": [184, 194, 216, 226]}, {"class": "NORM.XICAP", "bbox": [329, 88, 361, 120]}, {"class": "SUFF.FISML", "bbox": [3, 401, 35, 433]}, {"class": "SUFF.PSICAP", "bbox": [19, 169, 51, 201]}, {"class": "SUFF.ALPHASML", "bbox": [89, 208, 121, 240]}, {"class": "NORM.KSICAP", "bbox": [39, 203, 71, 235]}, {"class": "SUFF.OMEGACAP", "bbox": [156, 325, 188, 357]}, {"class": "SUFF.OMEGACAP", "bbox": [65, 1, 97, 33]}]