[{"class": "SUFF.BETASML", "bbox": [263, 170, 295, 202]}, {"class": "SUFF.ZETASML", "bbox": [358, 43, 390, 75]}, {"class": "SUFF.PIISML", "bbox": [190, 109, 222, 141]}, {"class": "NORM.IOTACAP", "bbox": [271, 211, 303, 243]}, {"class": "SUFF.TAUCAP", "bbox": [22, 298, 54, 330]}, {"class": "SUFF.EPSILONSML", "bbox": [254, 274, 286, 306]}, {"class": "NORM.GAMMASML", "bbox": [51, 192, 83, 224]}, {"class": "NORM.EPSILONSML", "bbox": [6, 355, 38, 387]}, {"class": "SUFF.ALPHACAP", "bbox": [316, 182, 348, 214]}, {"class": "NORM.OMIKRONCAP", "bbox": [154, 10, 186, 42]}, {"class": "SUFF.ALPHACAP", "bbox": [378, 413, 410, 445]}, {"class": "NORM.FICAP", "bbox": [380, 204, 412, 236]}, {"class": "SUFF.YPSILONSML", "bbox": [203, 29, 235, 61]}, {"class": "SUFF.ZETACAP", "bbox": [190, 152, 222, 184]}, {"class": "SUFF.OMEGACAP", "bbox": [8, 403, 40, 435]}, {"class": "SUFF.XISML", "bbox": [67, 312, 99, 344]}, {"class": "NORM.DELTASML", "bbox": [101, 301, 133, 333]}, {"class": "SUFF.DELTASML", "bbox": [46, 344, 78, 376]}, {"class": "SUFF.FISML", "bbox": [126, 73, 158, 105]}, {"class": "SUFF.KAPASML", "bbox": [185, 235, 217, 267]}]