[{"class": "NORM.LAMDACAP", "bbox": [314, 371, 346, 403]}, {"class": "NORM.LAMDASML", "bbox": [81, 385, 113, 417]}, {"class": "SUFF.GAMMACAP", "bbox": [288, 115, 320, 147]}, {"class": "NORM.SIGMACAP", "bbox": [213, 267, 245, 299]}, {"class": "SUFF.OMEGACAP", "bbox": [238, 354, 270, 386]}, {"class": "SUFF.OMEGASML", "bbox": [352, 303, 384, 335]}, {"class": "SUFF.XISML", "bbox": [222, 175, 254, 207]}, {"class": "SUFF.TAUCAP", "bbox": [362, 52, 394, 84]}, {"class": "SUFF.THETACAP", "bbox": [289, 313, 321, 345]}, {"class": "SUFF.KAPACAP", "bbox": [133, 15, 165, 47]}, {"class": "NORM.PSISML", "bbox": [161, 52, 193, 84]}, {"class": "SUFF.NICAP", "bbox": [331, 7, 363, 39]}, {"class": "SUFF.NISML", "bbox": [256, 144, 288, 176]}, {"class": "NORM.GAMMACAP", "bbox": [43, 110, 75, 142]}, {"class": "SUFF.LAMDACAP", "bbox": [230, 303, 262, 335]}, {"class": "NORM.BETASML", "bbox": [381, 336, 413, 368]}, {"class": "SUFF.EPSILONSML", "bbox": [139, 304, 171, 336]}, {"class": "NORM.ZETACAP", "bbox": [260, 74, 292, 106]}, {"class": "SUFF.ALPHASML", "bbox": [129, 402, 161, 434]}, {"class": "NORM.FISML", "bbox": [7, 191, 39, 223]}]