[{"class": "SUFF.HETACAP", "bbox": [209, 294, 241, 326]}, {"class": "NORM.TAUSML", "bbox": [113, 171, 145, 203]}, {"class": "NORM.OMIKRONSML", "bbox": [91, 371, 123, 403]}, {"class": "SUFF.XICAP", "bbox": [396, 94, 428, 126]}, {"class": "NORM.OMIKRONSML", "bbox": [380, 146, 412, 178]}, {"class": "NORM.BETACAP", "bbox": [291, 39, 323, 71]}, {"class": "SUFF.LAMDASML", "bbox": [62, 73, 94, 105]}, {"class": "NORM.KSICAP", "bbox": [321, 261, 353, 293]}, {"class": "NORM.NICAP", "bbox": [293, 145, 325, 177]}, {"class": "SUFF.LAMDACAP", "bbox": [267, 271, 299, 303]}, {"class": "NORM.SIGMACAP", "bbox": [121, 80, 153, 112]}, {"class": "NORM.HETACAP", "bbox": [241, 42, 273, 74]}, {"class": "SUFF.ROCAP", "bbox": [328, 295, 360, 327]}, {"class": "NORM.OMEGACAP", "bbox": [20, 47, 52, 79]}, {"class": "NORM.HETACAP", "bbox": [298, 352, 330, 384]}, {"class": "NORM.ROSML", "bbox": [335, 133, 367, 165]}, {"class": "NORM.ALPHASML", "bbox": [175, 116, 207, 148]}, {"class": "SUFF.EPSILONCAP", "bbox": [305, 2, 337, 34]}, {"class": "SUFF.OMEGASML", "bbox": [184, 361, 216, 393]}, {"class": "SUFF.YPSILONCAP", "bbox": [154, 200, 186, 232]}]