[{"class": "NORM.ALPHACAP", "bbox": [247, 241, 279, 273]}, {"class": "SUFF.NISML", "bbox": [115, 301, 147, 333]}, {"class": "NORM.HETACAP", "bbox": [246, 88, 278, 120]}, {"class": "NORM.YPSILONCAP", "bbox": [12, 263, 44, 295]}, {"class": "NORM.LAMDASML", "bbox": [155, 196, 187, 228]}, {"class": "NORM.TAUSML", "bbox": [117, 230, 149, 262]}, {"class": "SUFF.PSICAP", "bbox": [24, 333, 56, 365]}, {"class": "SUFF.KAPASML", "bbox": [360, 135, 392, 167]}, {"class": "SUFF.SIGMASML", "bbox": [303, 255, 335, 287]}, {"class": "SUFF.MICAP", "bbox": [369, 390, 401, 422]}, {"class": "NORM.HETACAP", "bbox": [55, 103, 87, 135]}, {"class": "SUFF.XISML", "bbox": [33, 195, 65, 227]}, {"class": "NORM.OMEGASML", "bbox": [184, 303, 216, 335]}, {"class": "SUFF.HETACAP", "bbox": [411, 119, 443, 151]}, {"class": "NORM.PSISML", "bbox": [76, 219, 108, 251]}, {"class": "NORM.KAPASML", "bbox": [351, 329, 383, 361]}, {"class": "NORM.MISML", "bbox": [129, 337, 161, 369]}, {"class": "SUFF.XICAP", "bbox": [113, 88, 145, 120]}, {"class": "NORM.KAPASML", "bbox": [275, 164, 307, 196]}, {"class": "SUFF.XISML", "bbox": [154, 411, 186, 443]}]