[{"class": "SUFF.OMIKRONCAP", "bbox": [5, 191, 37, 223]}, {"class": "SUFF.FISML", "bbox": [71, 387, 103, 419]}, {"class": "NORM.FICAP", "bbox": [299, 234, 331, 266]}, {"class": "NORM.ALPHASML", "bbox": [99, 297, 131, 329]}, {"class": "SUFF.PIISML", "bbox": [403, 111, 435, 143]}, {"class": "SUFF.ROCAP", "bbox": [196, 212, 228, 244]}, {"class": "NORM.PSICAP", "bbox": [160, 366, 192, 398]}, {"class": "NORM.SIGMASML", "bbox": [197, 297, 229, 329]}, {"class": "SUFF.SIGMASML", "bbox": [279, 107, 311, 139]}, {"class": "NORM.THETASML", "bbox": [84, 159, 116, 191]}, {"class": "NORM.GAMMACAP", "bbox": [22, 376, 54, 408]}, {"class": "NORM.IOTASML", "bbox": [22, 53, 54, 85]}, {"class": "SUFF.ZETASML", "bbox": [362, 405, 394, 437]}, {"class": "SUFF.MICAP", "bbox": [135, 268, 167, 300]}, {"class": "NORM.LAMDASML", "bbox": [343, 93, 375, 125]}, {"class": "NORM.ZETACAP", "bbox": [19, 123, 51, 155]}, {"class": "NORM.PSICAP", "bbox": [181, 140, 213, 172]}, {"class": "NORM.FICAP", "bbox": [412, 389, 444, 421]}, {"class": "SUFF.ZETACAP", "bbox": [234, 29, 266, 61]}, {"class": "NORM.LAMDASML", "bbox": [139, 58, 171, 90]}]