[{"class": "NORM.HETASML", "bbox": [205, 95, 237, 127]}, {"class": "NORM.DELTASML", "bbox": [12, 280, 44, 312]}, {"class": "SUFF.NISML", "bbox": [416, 85, 448, 117]}, {"class": "SUFF.HETACAP", "bbox": [167, 46, 199, 78]}, {"class": "NORM.YPSILONSML", "bbox": [349, 327, 381, 359]}, {"class": "SUFF.FISML", "bbox": [70, 231, 102, 263]}, {"class": "NORM.PIISML", "bbox": [383, 275, 415, 307]}, {"class": "NORM.ROCAP", "bbox": [128, 127, 160, 159]}, {"class": "SUFF.XICAP", "bbox": [184, 326, 216, 358]}, {"class": "SUFF.IOTACAP", "bbox": [218, 227, 250, 259]}, {"class": "SUFF.OMIKRONSML", "bbox": [106, 203, 138, 235]}, {"class": "NORM.PIISML", "bbox": [165, 390, 197, 422]}, {"class": "SUFF.THETACAP", "bbox": [145, 320, 177, 352]}, {"class": "NORM.IOTACAP", "bbox": [350, 273, 382, 305]}, {"class": "SUFF.IOTASML", "bbox": [222, 141, 254, 173]}, {"class": "SUFF.HETACAP", "bbox": [311, 295, 343, 327]}, {"class": "NORM.KSICAP", "bbox": [260, 289, 292, 321]}, {"class": "SUFF.OMEGASML", "bbox": [305, 7, 337, 39]}, {"class": "NORM.OMIKRONSML", "bbox": [184, 204, 216, 236]}, {"class": "NORM.THETACAP", "bbox": [404, 160, 436, 192]}]