[{"class": "NORM.TAUCAP", "bbox": [300, 264, 332, 296]}, {"class": "NORM.KAPACAP", "bbox": [23, 153, 55, 185]}, {"class": "NORM.EPSILONSML", "bbox": [216, 374, 248, 406]}, {"class": "NORM.ALPHASML", "bbox": [240, 101, 272, 133]}, {"class": "SUFF.PIISML", "bbox": [6, 323, 38, 355]}, {"class": "NORM.PIICAP", "bbox": [165, 229, 197, 261]}, {"class": "NORM.XICAP", "bbox": [332, 239, 364, 271]}, {"class": "NORM.EPSILONSML", "bbox": [371, 357, 403, 389]}, {"class": "NORM.NICAP", "bbox": [357, 165, 389, 197]}, {"class": "SUFF.MICAP", "bbox": [139, 12, 171, 44]}, {"class": "SUFF.ALPHACAP", "bbox": [137, 402, 169, 434]}, {"class": "SUFF.XISML", "bbox": [364, 72, 396, 104]}, {"class": "SUFF.NICAP", "bbox": [94, 87, 126, 119]}, {"class": "NORM.ZETASML", "bbox": [116, 48, 148, 80]}, {"class": "NORM.KSICAP", "bbox": [217, 196, 249, 228]}, {"class": "SUFF.NISML", "bbox": [318, 83, 350, 115]}, {"class": "NORM.LAMDASML", "bbox": [43, 375, 75, 407]}, {"class": "NORM.PIICAP", "bbox": [289, 177, 321, 209]}, {"class": "SUFF.HETASML", "bbox": [300, 209, 332, 241]}, {"class": "NORM.HETACAP", "bbox": [207, 255, 239, 287]}]