[{"class": "NORM.KAPACAP", "bbox": [97, 147, 129, 179]}, {"class": "SUFF.ALPHASML", "bbox": [113, 382, 145, 414]}, {"class": "SUFF.LAMDACAP", "bbox": [158, 119, 190, 151]}, {"class": "NORM.HETASML", "bbox": [242, 154, 274, 186]}, {"class": "SUFF.ZETACAP", "bbox": [72, 383, 104, 415]}, {"class": "NORM.OMEGASML", "bbox": [194, 351, 226, 383]}, {"class": "NORM.PSICAP", "bbox": [44, 271, 76, 303]}, {"class": "SUFF.HETASML", "bbox": [219, 284, 251, 316]}, {"class": "NORM.OMIKRONSML", "bbox": [227, 345, 259, 377]}, {"class": "NORM.LAMDACAP", "bbox": [168, 252, 200, 284]}, {"class": "SUFF.MICAP", "bbox": [291, 249, 323, 281]}, {"class": "NORM.YPSILONCAP", "bbox": [361, 174, 393, 206]}, {"class": "NORM.PIISML", "bbox": [290, 285, 322, 317]}, {"class": "SUFF.ALPHASML", "bbox": [150, 315, 182, 347]}, {"class": "NORM.SIGMASML", "bbox": [97, 259, 129, 291]}, {"class": "NORM.TAUSML", "bbox": [196, 2, 228, 34]}, {"class": "SUFF.XISML", "bbox": [172, 172, 204, 204]}, {"class": "SUFF.OMIKRONCAP", "bbox": [9, 359, 41, 391]}, {"class": "NORM.YPSILONSML", "bbox": [135, 36, 167, 68]}, {"class": "SUFF.DELTACAP", "bbox": [287, 128, 319, 160]}]