[{"class": "SUFF.ALPHASML", "bbox": [313, 40, 345, 72]}, {"class": "NORM.IOTASML", "bbox": [71, 172, 103, 204]}, {"class": "SUFF.SIGMASML", "bbox": [364, 248, 396, 280]}, {"class": "NORM.ZETACAP", "bbox": [262, 270, 294, 302]}, {"class": "NORM.FICAP", "bbox": [84, 2, 116, 34]}, {"class": "NORM.XISML", "bbox": [135, 236, 167, 268]}, {"class": "SUFF.ROSML", "bbox": [370, 330, 402, 362]}, {"class": "SUFF.IOTASML", "bbox": [388, 75, 420, 107]}, {"class": "NORM.LAMDACAP", "bbox": [194, 209, 226, 241]}, {"class": "NORM.LAMDASML", "bbox": [373, 287, 405, 319]}, {"class": "NORM.EPSILONSML", "bbox": [211, 25, 243, 57]}, {"class": "SUFF.TAUSML", "bbox": [83, 412, 115, 444]}, {"class": "NORM.IOTACAP", "bbox": [266, 355, 298, 387]}, {"class": "SUFF.SIGMACAP", "bbox": [296, 116, 328, 148]}, {"class": "SUFF.ZETACAP", "bbox": [6, 316, 38, 348]}, {"class": "SUFF.EPSILONCAP", "bbox": [269, 416, 301, 448]}, {"class": "SUFF.MISML", "bbox": [407, 137, 439, 169]}, {"class": "SUFF.KSICAP", "bbox": [119, 51, 151, 83]}, {"class": "SUFF.BETACAP", "bbox": [33, 97, 65, 129]}, {"class": "SUFF.THETASML", "bbox": [223, 81, 255, 113]}]