[{"class": "SUFF.HETASML", "bbox": [150, 402, 182, 434]}, {"class": "SUFF.KAPACAP", "bbox": [4, 44, 36, 76]}, {"class": "NORM.KSISML", "bbox": [288, 46, 320, 78]}, {"class": "NORM.PSICAP", "bbox": [107, 21, 139, 53]}, {"class": "SUFF.KSISML", "bbox": [376, 101, 408, 133]}, {"class": "SUFF.YPSILONCAP", "bbox": [181, 321, 213, 353]}, {"class": "NORM.DELTASML", "bbox": [330, 65, 362, 97]}, {"class": "NORM.HETASML", "bbox": [49, 263, 81, 295]}, {"class": "NORM.THETACAP", "bbox": [307, 309, 339, 341]}, {"class": "NORM.BETACAP", "bbox": [243, 340, 275, 372]}, {"class": "SUFF.THETACAP", "bbox": [12, 116, 44, 148]}, {"class": "NORM.ROCAP", "bbox": [253, 407, 285, 439]}, {"class": "NORM.YPSILONSML", "bbox": [63, 158, 95, 190]}, {"class": "NORM.FICAP", "bbox": [348, 13, 380, 45]}, {"class": "SUFF.THETASML", "bbox": [241, 194, 273, 226]}, {"class": "NORM.ALPHASML", "bbox": [179, 109, 211, 141]}, {"class": "SUFF.GAMMACAP", "bbox": [331, 386, 363, 418]}, {"class": "NORM.FICAP", "bbox": [158, 266, 190, 298]}, {"class": "SUFF.EPSILONSML", "bbox": [381, 272, 413, 304]}, {"class": "NORM.PSICAP", "bbox": [413, 219, 445, 251]}]