[{"class": "SUFF.GAMMACAP", "bbox": [7, 271, 39, 303]}, {"class": "NORM.ZETASML", "bbox": [197, 230, 229, 262]}, {"class": "SUFF.FISML", "bbox": [273, 234, 305, 266]}, {"class": "SUFF.THETACAP", "bbox": [294, 10, 326, 42]}, {"class": "NORM.GAMMACAP", "bbox": [128, 294, 160, 326]}, {"class": "NORM.FISML", "bbox": [385, 13, 417, 45]}, {"class": "NORM.PIISML", "bbox": [305, 402, 337, 434]}, {"class": "NORM.ZETACAP", "bbox": [152, 90, 184, 122]}, {"class": "NORM.FICAP", "bbox": [155, 29, 187, 61]}, {"class": "SUFF.FICAP", "bbox": [159, 236, 191, 268]}, {"class": "NORM.PIISML", "bbox": [56, 242, 88, 274]}, {"class": "SUFF.OMEGACAP", "bbox": [413, 260, 445, 292]}, {"class": "NORM.ROCAP", "bbox": [26, 358, 58, 390]}, {"class": "NORM.BETASML", "bbox": [95, 111, 127, 143]}, {"class": "NORM.IOTACAP", "bbox": [210, 98, 242, 130]}, {"class": "SUFF.ZETACAP", "bbox": [107, 362, 139, 394]}, {"class": "SUFF.LAMDACAP", "bbox": [363, 210, 395, 242]}, {"class": "SUFF.KSISML", "bbox": [55, 60, 87, 92]}, {"class": "NORM.MISML", "bbox": [337, 39, 369, 71]}, {"class": "NORM.BETACAP", "bbox": [232, 395, 264, 427]}]