[{"class": "NORM.PIICAP", "bbox": [366, 179, 398, 211]}, {"class": "SUFF.GAMMASML", "bbox": [189, 315, 221, 347]}, {"class": "NORM.XISML", "bbox": [254, 357, 286, 389]}, {"class": "SUFF.NICAP", "bbox": [409, 130, 441, 162]}, {"class": "SUFF.KAPASML", "bbox": [222, 93, 254, 125]}, {"class": "SUFF.OMEGACAP", "bbox": [376, 397, 408, 429]}, {"class": "NORM.HETASML", "bbox": [398, 56, 430, 88]}, {"class": "NORM.OMIKRONSML", "bbox": [3, 75, 35, 107]}, {"class": "NORM.SIGMASML", "bbox": [406, 163, 438, 195]}, {"class": "SUFF.ZETACAP", "bbox": [93, 295, 125, 327]}, {"class": "NORM.LAMDACAP", "bbox": [185, 371, 217, 403]}, {"class": "SUFF.BETACAP", "bbox": [395, 330, 427, 362]}, {"class": "SUFF.SIGMACAP", "bbox": [76, 192, 108, 224]}, {"class": "NORM.IOTACAP", "bbox": [150, 407, 182, 439]}, {"class": "NORM.KSICAP", "bbox": [120, 333, 152, 365]}, {"class": "NORM.NISML", "bbox": [287, 338, 319, 370]}, {"class": "NORM.IOTACAP", "bbox": [66, 386, 98, 418]}, {"class": "SUFF.TAUCAP", "bbox": [7, 277, 39, 309]}, {"class": "NORM.THETACAP", "bbox": [48, 303, 80, 335]}, {"class": "NORM.FICAP", "bbox": [379, 88, 411, 120]}]