[{"class": "SUFF.EPSILONSML", "bbox": [300, 224, 332, 256]}, {"class": "SUFF.ROSML", "bbox": [374, 315, 406, 347]}, {"class": "NORM.DELTACAP", "bbox": [385, 347, 417, 379]}, {"class": "NORM.ZETACAP", "bbox": [84, 402, 116, 434]}, {"class": "SUFF.MICAP", "bbox": [398, 67, 430, 99]}, {"class": "SUFF.NISML", "bbox": [311, 31, 343, 63]}, {"class": "SUFF.TAUCAP", "bbox": [399, 167, 431, 199]}, {"class": "SUFF.HETASML", "bbox": [269, 75, 301, 107]}, {"class": "NORM.IOTASML", "bbox": [64, 46, 96, 78]}, {"class": "SUFF.KSISML", "bbox": [30, 264, 62, 296]}, {"class": "NORM.HETACAP", "bbox": [393, 218, 425, 250]}, {"class": "SUFF.NISML", "bbox": [53, 5, 85, 37]}, {"class": "NORM.NISML", "bbox": [241, 176, 273, 208]}, {"class": "SUFF.XICAP", "bbox": [202, 145, 234, 177]}, {"class": "SUFF.FISML", "bbox": [349, 363, 381, 395]}, {"class": "NORM.GAMMASML", "bbox": [125, 279, 157, 311]}, {"class": "NORM.NISML", "bbox": [25, 381, 57, 413]}, {"class": "NORM.ALPHASML", "bbox": [49, 81, 81, 113]}, {"class": "SUFF.LAMDACAP", "bbox": [31, 48, 63, 80]}, {"class": "NORM.THETACAP", "bbox": [182, 403, 214, 435]}]