[{"class": "NORM.LAMDACAP", "bbox": [132, 109, 164, 141]}, {"class": "NORM.TAUSML", "bbox": [17, 267, 49, 299]}, {"class": "NORM.LAMDASML", "bbox": [256, 264, 288, 296]}, {"class": "SUFF.BETACAP", "bbox": [127, 169, 159, 201]}, {"class": "NORM.IOTACAP", "bbox": [96, 310, 128, 342]}, {"class": "NORM.KAPACAP", "bbox": [274, 76, 306, 108]}, {"class": "NORM.DELTASML", "bbox": [35, 134, 67, 166]}, {"class": "SUFF.PIICAP", "bbox": [382, 236, 414, 268]}, {"class": "NORM.DELTACAP", "bbox": [191, 76, 223, 108]}, {"class": "SUFF.TAUCAP", "bbox": [317, 287, 349, 319]}, {"class": "NORM.KSISML", "bbox": [206, 318, 238, 350]}, {"class": "SUFF.DELTASML", "bbox": [87, 231, 119, 263]}, {"class": "SUFF.PSICAP", "bbox": [308, 65, 340, 97]}, {"class": "NORM.YPSILONSML", "bbox": [134, 270, 166, 302]}, {"class": "SUFF.DELTASML", "bbox": [188, 363, 220, 395]}, {"class": "SUFF.NISML", "bbox": [349, 199, 381, 231]}, {"class": "NORM.DELTASML", "bbox": [312, 125, 344, 157]}, {"class": "SUFF.KSISML", "bbox": [288, 345, 320, 377]}, {"class": "SUFF.THETASML", "bbox": [54, 325, 86, 357]}, {"class": "NORM.OMEGACAP", "bbox": [249, 10, 281, 42]}]