[{"class": "NORM.NISML", "bbox": [323, 38, 355, 70]}, {"class": "NORM.EPSILONSML", "bbox": [70, 184, 102, 216]}, {"class": "NORM.KAPASML", "bbox": [176, 393, 208, 425]}, {"class": "SUFF.ROCAP", "bbox": [256, 120, 288, 152]}, {"class": "NORM.LAMDACAP", "bbox": [164, 218, 196, 250]}, {"class": "NORM.IOTASML", "bbox": [44, 37, 76, 69]}, {"class": "NORM.ALPHACAP", "bbox": [272, 268, 304, 300]}, {"class": "SUFF.NICAP", "bbox": [406, 161, 438, 193]}, {"class": "NORM.BETACAP", "bbox": [361, 92, 393, 124]}, {"class": "SUFF.PSISML", "bbox": [208, 111, 240, 143]}, {"class": "NORM.ZETACAP", "bbox": [32, 312, 64, 344]}, {"class": "NORM.DELTASML", "bbox": [291, 187, 323, 219]}, {"class": "SUFF.ROSML", "bbox": [258, 320, 290, 352]}, {"class": "NORM.XICAP", "bbox": [333, 336, 365, 368]}, {"class": "SUFF.SIGMACAP", "bbox": [126, 116, 158, 148]}, {"class": "SUFF.SIGMASML", "bbox": [34, 222, 66, 254]}, {"class": "NORM.KAPASML", "bbox": [157, 71, 189, 103]}, {"class": "SUFF.EPSILONSML", "bbox": [118, 35, 150, 67]}, {"class": "NORM.MICAP", "bbox": [82, 224, 114, 256]}, {"class": "SUFF.GAMMASML", "bbox": [191, 51, 223, 83]}]