[{"class": "NORM.FISML", "bbox": [51, 270, 83, 302]}, {"class": "SUFF.LAMDASML", "bbox": [358, 253, 390, 285]}, {"class": "SUFF.OMEGACAP", "bbox": [392, 329, 424, 361]}, {"class": "SUFF.TAUCAP", "bbox": [96, 299, 128, 331]}, {"class": "SUFF.PSICAP", "bbox": [147, 110, 179, 142]}, {"class": "NORM.HETACAP", "bbox": [209, 118, 241, 150]}, {"class": "NORM.KAPASML", "bbox": [210, 323, 242, 355]}, {"class": "SUFF.ZETACAP", "bbox": [327, 167, 359, 199]}, {"class": "SUFF.MICAP", "bbox": [306, 325, 338, 357]}, {"class": "SUFF.THETACAP", "bbox": [331, 38, 363, 70]}, {"class": "SUFF.THETASML", "bbox": [220, 286, 252, 318]}, {"class": "NORM.LAMDASML", "bbox": [315, 123, 347, 155]}, {"class": "NORM.ZETACAP", "bbox": [188, 35, 220, 67]}, {"class": "NORM.MICAP", "bbox": [134, 242, 166, 274]}, {"class": "NORM.XICAP", "bbox": [46, 397, 78, 429]}, {"class": "SUFF.MICAP", "bbox": [332, 399, 364, 431]}, {"class": "NORM.PSICAP", "bbox": [77, 217, 109, 249]}, {"class": "SUFF.BETASML", "bbox": [188, 409, 220, 441]}, {"class": "NORM.LAMDACAP", "bbox": [99, 349, 131, 381]}, {"class": "SUFF.TAUSML", "bbox": [91, 252, 123, 284]}]