[{"class": "NORM.DELTACAP", "bbox": [405, 92, 437, 124]}, {"class": "SUFF.MISML", "bbox": [131, 101, 163, 133]}, {"class": "SUFF.YPSILONSML", "bbox": [339, 309, 371, 341]}, {"class": "SUFF.PIISML", "bbox": [221, 269, 253, 301]}, {"class": "NORM.BETASML", "bbox": [202, 210, 234, 242]}, {"class": "SUFF.XICAP", "bbox": [391, 132, 423, 164]}, {"class": "SUFF.DELTACAP", "bbox": [361, 12, 393, 44]}, {"class": "SUFF.GAMMASML", "bbox": [279, 145, 311, 177]}, {"class": "NORM.EPSILONCAP", "bbox": [5, 214, 37, 246]}, {"class": "SUFF.YPSILONSML", "bbox": [129, 133, 161, 165]}, {"class": "SUFF.PIICAP", "bbox": [238, 405, 270, 437]}, {"class": "NORM.XISML", "bbox": [283, 377, 315, 409]}, {"class": "SUFF.MISML", "bbox": [380, 252, 412, 284]}, {"class": "NORM.ALPHACAP", "bbox": [275, 219, 307, 251]}, {"class": "NORM.PSISML", "bbox": [117, 306, 149, 338]}, {"class": "NORM.ROCAP", "bbox": [346, 53, 378, 85]}, {"class": "SUFF.TAUCAP", "bbox": [108, 34, 140, 66]}, {"class": "NORM.HETASML", "bbox": [405, 328, 437, 360]}, {"class": "SUFF.SIGMASML", "bbox": [348, 239, 380, 271]}, {"class": "NORM.THETASML", "bbox": [147, 49, 179, 81]}]