[{"class": "SUFF.FISML", "bbox": [5, 265, 37, 297]}, {"class": "NORM.KSISML", "bbox": [151, 176, 183, 208]}, {"class": "NORM.XISML", "bbox": [378, 44, 410, 76]}, {"class": "SUFF.OMEGACAP", "bbox": [90, 29, 122, 61]}, {"class": "NORM.ROCAP", "bbox": [34, 71, 66, 103]}, {"class": "SUFF.MICAP", "bbox": [92, 337, 124, 369]}, {"class": "SUFF.GAMMACAP", "bbox": [17, 232, 49, 264]}, {"class": "NORM.ROSML", "bbox": [114, 266, 146, 298]}, {"class": "NORM.IOTASML", "bbox": [71, 304, 103, 336]}, {"class": "SUFF.NICAP", "bbox": [136, 329, 168, 361]}, {"class": "NORM.THETASML", "bbox": [293, 205, 325, 237]}, {"class": "NORM.YPSILONSML", "bbox": [205, 366, 237, 398]}, {"class": "NORM.ALPHACAP", "bbox": [59, 391, 91, 423]}, {"class": "NORM.THETACAP", "bbox": [19, 298, 51, 330]}, {"class": "NORM.HETACAP", "bbox": [256, 76, 288, 108]}, {"class": "NORM.FICAP", "bbox": [153, 266, 185, 298]}, {"class": "NORM.YPSILONSML", "bbox": [280, 114, 312, 146]}, {"class": "SUFF.MICAP", "bbox": [155, 97, 187, 129]}, {"class": "NORM.KAPACAP", "bbox": [210, 172, 242, 204]}, {"class": "SUFF.FISML", "bbox": [376, 1, 408, 33]}]