[{"class": "SUFF.HETASML", "bbox": [220, 147, 252, 179]}, {"class": "SUFF.OMIKRONCAP", "bbox": [257, 272, 289, 304]}, {"class": "SUFF.HETACAP", "bbox": [369, 32, 401, 64]}, {"class": "SUFF.OMEGASML", "bbox": [102, 365, 134, 397]}, {"class": "SUFF.YPSILONSML", "bbox": [330, 57, 362, 89]}, {"class": "SUFF.ZETASML", "bbox": [140, 177, 172, 209]}, {"class": "NORM.PSISML", "bbox": [178, 162, 210, 194]}, {"class": "NORM.XICAP", "bbox": [413, 184, 445, 216]}, {"class": "NORM.THETASML", "bbox": [164, 269, 196, 301]}, {"class": "NORM.THETACAP", "bbox": [364, 341, 396, 373]}, {"class": "SUFF.IOTASML", "bbox": [12, 88, 44, 120]}, {"class": "SUFF.YPSILONSML", "bbox": [62, 302, 94, 334]}, {"class": "NORM.ROSML", "bbox": [331, 297, 363, 329]}, {"class": "NORM.LAMDACAP", "bbox": [125, 51, 157, 83]}, {"class": "SUFF.FICAP", "bbox": [59, 363, 91, 395]}, {"class": "NORM.ROCAP", "bbox": [248, 65, 280, 97]}, {"class": "SUFF.KSISML", "bbox": [411, 369, 443, 401]}, {"class": "SUFF.GAMMASML", "bbox": [379, 165, 411, 197]}, {"class": "NORM.MICAP", "bbox": [395, 97, 427, 129]}, {"class": "NORM.DELTASML", "bbox": [266, 184, 298, 216]}]