[{"class": "SUFF.GAMMACAP", "bbox": [276, 327, 308, 359]}, {"class": "SUFF.GAMMACAP", "bbox": [361, 191, 393, 223]}, {"class": "NORM.PSISML", "bbox": [294, 157, 326, 189]}, {"class": "NORM.MISML", "bbox": [211, 10, 243, 42]}, {"class": "SUFF.FISML", "bbox": [145, 116, 177, 148]}, {"class": "SUFF.OMEGACAP", "bbox": [311, 52, 343, 84]}, {"class": "SUFF.KSISML", "bbox": [108, 394, 140, 426]}, {"class": "SUFF.MISML", "bbox": [367, 392, 399, 424]}, {"class": "SUFF.ROCAP", "bbox": [222, 188, 254, 220]}, {"class": "NORM.TAUSML", "bbox": [224, 151, 256, 183]}, {"class": "SUFF.PIISML", "bbox": [27, 295, 59, 327]}, {"class": "SUFF.ALPHASML", "bbox": [181, 346, 213, 378]}, {"class": "SUFF.FICAP", "bbox": [295, 401, 327, 433]}, {"class": "NORM.KSISML", "bbox": [33, 386, 65, 418]}, {"class": "NORM.IOTACAP", "bbox": [238, 108, 270, 140]}, {"class": "SUFF.LAMDACAP", "bbox": [124, 316, 156, 348]}, {"class": "NORM.ROSML", "bbox": [59, 242, 91, 274]}, {"class": "SUFF.KSISML", "bbox": [292, 207, 324, 239]}, {"class": "SUFF.GAMMACAP", "bbox": [398, 313, 430, 345]}, {"class": "SUFF.SIGMASML", "bbox": [162, 32, 194, 64]}]