[{"class": "SUFF.GAMMACAP", "bbox": [283, 75, 315, 107]}, {"class": "SUFF.THETASML", "bbox": [155, 334, 187, 366]}, {"class": "SUFF.THETACAP", "bbox": [117, 183, 149, 215]}, {"class": "NORM.GAMMASML", "bbox": [407, 34, 439, 66]}, {"class": "SUFF.XISML", "bbox": [123, 404, 155, 436]}, {"class": "NORM.PSICAP", "bbox": [356, 322, 388, 354]}, {"class": "SUFF.THETACAP", "bbox": [182, 375, 214, 407]}, {"class": "SUFF.BETASML", "bbox": [37, 349, 69, 381]}, {"class": "SUFF.OMIKRONCAP", "bbox": [80, 205, 112, 237]}, {"class": "NORM.ALPHACAP", "bbox": [77, 378, 109, 410]}, {"class": "SUFF.OMEGASML", "bbox": [78, 151, 110, 183]}, {"class": "SUFF.EPSILONCAP", "bbox": [209, 173, 241, 205]}, {"class": "NORM.KSICAP", "bbox": [266, 222, 298, 254]}, {"class": "SUFF.ROSML", "bbox": [375, 209, 407, 241]}, {"class": "SUFF.PSICAP", "bbox": [17, 246, 49, 278]}, {"class": "SUFF.OMEGASML", "bbox": [125, 249, 157, 281]}, {"class": "NORM.LAMDACAP", "bbox": [119, 282, 151, 314]}, {"class": "SUFF.EPSILONSML", "bbox": [85, 64, 117, 96]}, {"class": "SUFF.LAMDASML", "bbox": [128, 40, 160, 72]}, {"class": "NORM.LAMDACAP", "bbox": [327, 238, 359, 270]}]