[{"class": "SUFF.TAUCAP", "bbox": [94, 397, 126, 429]}, {"class": "SUFF.KAPACAP", "bbox": [345, 374, 377, 406]}, {"class": "SUFF.THETACAP", "bbox": [144, 236, 176, 268]}, {"class": "NORM.PSISML", "bbox": [74, 52, 106, 84]}, {"class": "NORM.EPSILONCAP", "bbox": [228, 7, 260, 39]}, {"class": "SUFF.GAMMASML", "bbox": [191, 280, 223, 312]}, {"class": "NORM.FICAP", "bbox": [12, 270, 44, 302]}, {"class": "SUFF.EPSILONSML", "bbox": [353, 122, 385, 154]}, {"class": "NORM.KSICAP", "bbox": [54, 264, 86, 296]}, {"class": "SUFF.PIISML", "bbox": [149, 34, 181, 66]}, {"class": "NORM.ZETASML", "bbox": [26, 4, 58, 36]}, {"class": "NORM.GAMMACAP", "bbox": [67, 4, 99, 36]}, {"class": "NORM.PIICAP", "bbox": [218, 77, 250, 109]}, {"class": "NORM.THETASML", "bbox": [413, 30, 445, 62]}, {"class": "SUFF.LAMDACAP", "bbox": [256, 99, 288, 131]}, {"class": "SUFF.OMIKRONCAP", "bbox": [355, 306, 387, 338]}, {"class": "SUFF.THETACAP", "bbox": [303, 18, 335, 50]}, {"class": "NORM.ALPHASML", "bbox": [77, 99, 109, 131]}, {"class": "NORM.OMIKRONSML", "bbox": [176, 153, 208, 185]}, {"class": "SUFF.MICAP", "bbox": [326, 183, 358, 215]}]